stactask/__init__.py
stactask/__version__.py
stactask/asset_io.py
stactask/config.py
stactask/exceptions.py
stactask/logging.py
stactask/payload.py
stactask/py.typed
stactask/task.py
stactask/utils.py
stactask-0.7.0.dist-info/METADATA
stactask-0.7.0.dist-info/WHEEL
stactask-0.7.0.dist-info/licenses/LICENSE
stactask-0.7.0.dist-info/RECORD
