Metadata-Version: 2.4
Name: stactask
Version: 0.7.0
Summary: Class interface for running custom algorithms and workflows on STAC Items
Project-URL: Issues, https://github.com/stac-utils/stactask/issues
Project-URL: Github, https://github.com/stac-utils/stac-task
Project-URL: Changelog, https://github.com/stac-utils/stac-task/blob/main/CHANGELOG.md
Author-email: Matthew Hanson <matt.a.hanson@gmail.com>
Maintainer-email: Ian Cooke <ircwaves@gmail.com>
License: Apache-2.0
License-File: LICENSE
Keywords: STAC,catalog,imagery,pystac,raster
Classifier: Development Status :: 2 - Pre-Alpha
Classifier: Intended Audience :: Developers
Classifier: License :: OSI Approved :: Apache Software License
Classifier: Natural Language :: English
Classifier: Programming Language :: Python :: 3
Classifier: Programming Language :: Python :: 3.10
Classifier: Programming Language :: Python :: 3.11
Classifier: Programming Language :: Python :: 3.12
Classifier: Programming Language :: Python :: 3.13
Requires-Python: >=3.10
Requires-Dist: boto3-utils>=0.3.2
Requires-Dist: fsspec>=2022.8.2
Requires-Dist: jsonpath-ng>=1.5.3
Requires-Dist: pystac>=1.6
Requires-Dist: python-dateutil>=2.7.0
Requires-Dist: requests>=2.28.1
Requires-Dist: s3fs>=2022.8.2
Requires-Dist: stac-asset>=0.3.0
